.coveragerc
CHANGELOG.md
LICENSE
MANIFEST.in
README.md
pyproject.toml
setup.py
docs/.gitignore
docs/Makefile
docs/clear-automodapis.sh
docs/cli.rst
docs/conf.py
docs/index.rst
docs/installation.rst
docs/make.bat
docs/manual.rst
docs/overview.rst
docs/pipeline.rst
docs/studies.rst
docs/toasting.rst
docs/_static/copybutton.js
docs/_templates/layout.html
docs/api/toasty.TilingMethod.rst
docs/api/toasty.builder.Builder.rst
docs/api/toasty.builder.rst
docs/api/toasty.cli.die.rst
docs/api/toasty.cli.entrypoint.rst
docs/api/toasty.cli.rst
docs/api/toasty.cli.warn.rst
docs/api/toasty.collection.CollectionLoader.rst
docs/api/toasty.collection.ImageCollection.rst
docs/api/toasty.collection.RubinDirectoryCollection.rst
docs/api/toasty.collection.SimpleFitsCollection.rst
docs/api/toasty.collection.load.rst
docs/api/toasty.collection.rst
docs/api/toasty.fits_tiler.FitsTiler.rst
docs/api/toasty.fits_tiler.rst
docs/api/toasty.image.Image.rst
docs/api/toasty.image.ImageDescription.rst
docs/api/toasty.image.ImageLoader.rst
docs/api/toasty.image.ImageMode.rst
docs/api/toasty.image.get_format_vertical_parity_sign.rst
docs/api/toasty.image.rst
docs/api/toasty.merge.TileMerger.rst
docs/api/toasty.merge.averaging_merger.rst
docs/api/toasty.merge.cascade_images.rst
docs/api/toasty.merge.rst
docs/api/toasty.multi_tan.MultiTanProcessor.rst
docs/api/toasty.multi_tan.rst
docs/api/toasty.openexr.load_openexr.rst
docs/api/toasty.openexr.rst
docs/api/toasty.par_util.resolve_parallelism.rst
docs/api/toasty.par_util.rst
docs/api/toasty.pipeline.CandidateInput.rst
docs/api/toasty.pipeline.ImageSource.rst
docs/api/toasty.pipeline.NotActionableError.rst
docs/api/toasty.pipeline.PipelineIo.rst
docs/api/toasty.pipeline.astropix.AstroPixCandidateInput.rst
docs/api/toasty.pipeline.astropix.AstroPixImageSource.rst
docs/api/toasty.pipeline.astropix.rst
docs/api/toasty.pipeline.azure_io.AzureBlobPipelineIo.rst
docs/api/toasty.pipeline.azure_io.assert_enabled.rst
docs/api/toasty.pipeline.azure_io.rst
toasty.egg-info/PKG-INFO
toasty.egg-info/SOURCES.txt
toasty.egg-info/dependency_links.txt
toasty.egg-info/entry_points.txt
toasty.egg-info/requires.txt
toasty.egg-info/top_level.txt
